client/__init__.py
client/dict_parse.py
client/main.py
objects/__init__.py
objects/food.py
objects/nutrient_dict.py
service/__init__.py
service/food.py
service/report.py
service/search.py
nomsapi-0.1.3.dist-info/LICENSE
nomsapi-0.1.3.dist-info/METADATA
nomsapi-0.1.3.dist-info/WHEEL
nomsapi-0.1.3.dist-info/top_level.txt
nomsapi-0.1.3.dist-info/RECORD
