Metadata-Version: 2.1
Name: nomsapi
Version: 0.1.3
Summary: A fun and simple Python package that allows you to work with highly detailed nutrition data
Home-page: https://github.com/noahtren/noms
Author: updated from Noah Trenaman
Author-email: hello@noahtrenaman.com
License: UNKNOWN
Platform: UNKNOWN
Classifier: Programming Language :: Python :: 3
Classifier: License :: OSI Approved :: MIT License
Classifier: Operating System :: OS Independent
